pd_window_decorators/__init__.py
pd_window_decorators/decorators.py
pd_window_decorators-0.0.1.dist-info/LICENSE
pd_window_decorators-0.0.1.dist-info/METADATA
pd_window_decorators-0.0.1.dist-info/WHEEL
pd_window_decorators-0.0.1.dist-info/top_level.txt
pd_window_decorators-0.0.1.dist-info/RECORD
