Metadata-Version: 2.1
Name: pd-window-decorators
Version: 0.0.1
Summary: A decorator for applying a moving window to a function that consumes and returns a Pandas DataFrame.
Author-email: Orphoros <contact@orphoros.com>
License: Copyright (c) 2023 Orphoros
Project-URL: homepage, https://github.com/Orphoros/PdWindowDecorators
Project-URL: documentation, https://github.com/Orphoros/PdWindowDecorators
Project-URL: repository, https://github.com/Orphoros/PdWindowDecorators
Keywords: pandas,sliding window,decorator,function,dataframe,data science
Classifier: Programming Language :: Python :: 3
Classifier: License :: OSI Approved :: MIT License
Classifier: Operating System :: OS Independent
Requires-Python: >=3.9
License-File: LICENSE
Requires-Dist: pandas >=1.3.0
Requires-Dist: numpy >=1.21.0
